Synthesis/fa_by_ha.v

// STRUCTURAL OR GATE LEVEL MODELLING OF FULL ADDER USING THE HALF ADDER
// SOURCE CODE 

module half_adder(a,b,sum,Carry);  // Half adder instance
       input a,b;    
       output  wire sum,Carry;
       assign sum = a^b;        
  	   assign Carry = a&b;
endmodule

module full_adder (a,b,Cin,sum,Cout); // Designing full adder module using half adder instance
       input a,b,Cin;
       output sum,Cout;
   	   wire C1,S1,C2;
   	   half_adder HA1(a,b,S1,C1); // For the first half adder instance
   	   half_adder HA2(Cin,S1,sum,C2); // For the first half adder instance
   	   or (Cout,C1,C2); // The output & input of OR gate
endmodule

tb_fa.v
// TESTBENCH CODE

module tb_fa();
       reg a,b,Cin;  // Inputs of the full adder
       wire sum,Cout; // Outputs of the full adder 
initial begin
    $dumpfile("full_adder.vcd");  // all the binaries will be dumped into that file
    $dumpvars; // all the variables will be dumped into that file
    $display("CHECKING THE OUTPUTS OF THE FULL ADDER");
    $display ("Time \t  A \t  B  \t  Cin  \t  S  \t   Cout");
    $monitor("%g \t  %b \t  %b \t  %b \t  %b \t  %b", $time,a,b,Cin,sum,Cout); // monitoring the change of output in accordance with change of input
    
    // applying the inputs to test the characteristics of the full adder
    
    #0    {a,b,Cin}=3'b000; 
    #5   {a,b,Cin}=3'b001;
    #10 {a,b,Cin}=3'b010;
    #15 {a,b,Cin}=3'b011;
    #20 {a,b,Cin}=3'b100;
    #25 {a,b,Cin}=3'b101;
    #30 {a,b,Cin}=3'b110;
    #35 {a,b,Cin}=3'b111;
    #40 $finish ;
end
full_adder FA(a,b,Cin,sum,Cout);
endmodule

full_adder.vcd
$date
	Thu May 16 13:07:23 2024
$end
$version
	Icarus Verilog
$end
$timescale
	1s
$end
$scope module tb_fa $end
$var wire 1 ! sum $end
$var wire 1 " Cout $end
$var reg 1 # Cin $end
$var reg 1 $ a $end
$var reg 1 % b $end
$scope module FA $end
$var wire 1 # Cin $end
$var wire 1 " Cout $end
$var wire 1 $ a $end
$var wire 1 % b $end
$var wire 1 ! sum $end
$var wire 1 & S1 $end
$var wire 1 ' C2 $end
$var wire 1 ( C1 $end
$scope module HA1 $end
$var wire 1 ( Carry $end
$var wire 1 $ a $end
$var wire 1 % b $end
$var wire 1 & sum $end
$upscope $end
$scope module HA2 $end
$var wire 1 ' Carry $end
$var wire 1 # a $end
$var wire 1 & b $end
$var wire 1 ! sum $end
$upscope $end
$upscope $end
$upscope $end
$enddefinitions $end
#0
$dumpvars
0(
0'
0&
0%
0$
0#
0"
0!
$end
#5
1!
1#
#15
1&
1!
1%
0#
#30
1"
0!
1'
1#
#50
0"
1!
0'
1$
0%
0#
#75
1"
0!
1'
1#
#105
0&
1(
0!
0'
1%
0#
#140
1!
1#
